parseratorvariable/__init__.py
parseratorvariable/predicates.py
parseratorvariable-1.0.0.dist-info/METADATA
parseratorvariable-1.0.0.dist-info/WHEEL
parseratorvariable-1.0.0.dist-info/top_level.txt
parseratorvariable-1.0.0.dist-info/RECORD
