Metadata-Version: 2.1
Name: parseratorvariable
Version: 1.0.0
Summary: Structured variable type for dedupe
Home-page: https://github.com/datamade/parseratorvariables
License: The MIT License: http://www.opensource.org/licenses/mit-license.php
Requires-Dist: dedupe >=3.0.0
Requires-Dist: numpy
Requires-Dist: probableparsing
